pandasdate/__init__.py
pandasdate/pandasdate.py
pandasdate-1.0.2.dist-info/METADATA
pandasdate-1.0.2.dist-info/WHEEL
pandasdate-1.0.2.dist-info/top_level.txt
pandasdate-1.0.2.dist-info/RECORD
