Metadata-Version: 2.1
Name: pandasdate
Version: 1.0.2
Summary: A pandas DataFrame extension with date tracking
Home-page: https://github.com/yourusername/pandasdate
Author: Eshan Jayasundara
Author-email: jmeshangj@gmail.com
Classifier: Programming Language :: Python :: 3
Classifier: License :: OSI Approved :: MIT License
Classifier: Operating System :: OS Independent
Requires-Python: >=3.6
Requires-Dist: pandas >=2.2.2
Requires-Dist: numpy >=1.26.3
Requires-Dist: pyarrow >=18.0.0
Requires-Dist: openpyxl >=3.1.5
